setup.py
matrix_algebra_udsnd/__init__.py
matrix_algebra_udsnd/matrix_algebra.py
matrix_algebra_udsnd.egg-info/PKG-INFO
matrix_algebra_udsnd.egg-info/SOURCES.txt
matrix_algebra_udsnd.egg-info/dependency_links.txt
matrix_algebra_udsnd.egg-info/not-zip-safe
matrix_algebra_udsnd.egg-info/top_level.txt