Metadata-Version: 1.0
Name: matrix-algebra-udsnd
Version: 0.1
Summary: Matrix algebra
Home-page: UNKNOWN
Author: UNKNOWN
Author-email: UNKNOWN
License: UNKNOWN
Platform: UNKNOWN
